rssynergia
