Metadata-Version: 1.1
Name: rssynergia
Version: 20180115.103457
Summary: Support tools for Synergia
Home-page: https://github.com/radiasoft/rssynergia
Author: RadiaSoft LLC
Author-email: pip@radiasoft.net
License: http://www.apache.org/licenses/LICENSE-2.0.html
Platform: UNKNOWN
Classifier: Development Status :: 2 - Pre-Alpha
Classifier: Environment :: Console
Classifier: Intended Audience :: Developers
Classifier: License :: OSI Approved :: Apache Software License
Classifier: Natural Language :: English
Classifier: Programming Language :: Python :: 2
Classifier: Programming Language :: Python :: 2.7
Classifier: Programming Language :: Python
Classifier: Topic :: Utilities
